[
    {
        "id": "Rosch",
        "name": "Rosch",
        "gender": "male",
        "basetraits": [
            "Warrior"
        ], 
        "race": "Human", 
        "random_trait_groups": [
            [
                [
                    1, 
                    3
                ], 
                [
                    [
                        "Courageous", 
                        50
                    ], 
                    [
                        "Vicious", 
                        50
                    ], 
                    [
                        "Aggressive", 
                        50
                    ]
                ]
            ]
        ]
    }
]